{
    "Ideologías Totalitarias": [
        "Supresión de la Oposición",
        "Culto al Líder",
        "Nacionalismo Exacerbado",
        "Militarismo"
    ],
    "Expansionismo Territorial": [
        "Lebensraum (Espacio Vital) Nazi",
        "Intervención Italiana en Etiopía",
        "Anschluss (Anexión de Austria)",
        "Invasión de Checoslovaquia"
    ],
    "Racismo y Antisemitismo": [
        "Leyes de Núremberg",
        "La Solución Final",
        "Propaganda Antisemita"
    ],
    "Crisis Económica y Descontento Social": [
        "Hiperinflación en Alemania",
        "Desempleo Masivo",
        "Aprovechamiento del Resentimiento Popular"
    ],
    "Debilidad de la Liga de Naciones": [
        "Falta de Poder Coercitivo",
        "Política de Apaciguamiento",
        "Incumplimiento de Tratados"
    ],
    "Alianzas Estratégicas": [
        "Eje Roma-Berlín-Tokio",
        "Pacto de Acero (Alemania e Italia)",
        "Pacto Anti-Komintern"
    ],
    "Causas Directas de la Guerra": [
        "Invasión de Polonia",
        "Declaraciones de Guerra de Francia y Reino Unido"
    ],
    "Respuesta Aliada al Expansionismo": [
        "Política de Apaciguamiento",
        "Declaración de Guerra",
        "Formación de la Coalición Aliada"
    ]
}